validate_aws_policies/__init__.py
validate_aws_policies/validate_policies.py
validate_aws_policies/version.py
validate_aws_policies/iam_access_analyzer/__init__.py
validate_aws_policies/iam_access_analyzer/iam_access_analyzer.py
validate_aws_policies/ops/__init__.py
validate_aws_policies/ops/ops.py
validate_aws_policies-2.0.2.dist-info/METADATA
validate_aws_policies-2.0.2.dist-info/WHEEL
validate_aws_policies-2.0.2.dist-info/entry_points.txt
validate_aws_policies-2.0.2.dist-info/licenses/LICENSE
validate_aws_policies-2.0.2.dist-info/RECORD
