Metadata-Version: 2.3
Name: validate_aws_policies
Version: 2.0.2
Summary: A tool for scan policies using AWS access Analyzer API and create reports 
Project-URL: Homepage, https://github.com/velez94/validate-aws-policies/
Project-URL: Bug Tracker, https://github.com/velez94/validate-aws-policies/issues
Author-email: Alejandro Velez <avelez@labvel.io>
License: Copyright (c) [2024] [Alejandro Velez]
License-File: LICENSE
Classifier: License :: OSI Approved :: Apache Software License
Classifier: Operating System :: OS Independent
Classifier: Programming Language :: Python :: 3
Requires-Python: >=3.8
Requires-Dist: argcomplete>=3.4.0
Requires-Dist: argparse>=1.4.0
Requires-Dist: boto3>=1.34.138
Requires-Dist: colorama>=0.4.6
Requires-Dist: json2html>=1.3.0
Requires-Dist: pdfkit>=1.0.0
Requires-Dist: zipp>=3.19.2
